{
	"101CustomIZ1：光茵荏苒": "<size=18>Chapter 1: 시간의 잔디밭\n\n\n\n\n\n\n\n\n\n\n\n\n\n\n\n\n\n\n\n나, 좀비 퍼즐에 오신 것을 환영합니다! 최상의 경험을 위해 플레이 전 난이도를 권장 설정으로 변경해 주세요.\n여러분의 목표는 좀비들이 각 라인 끝에 있는 뇌를 모두 먹게 하는 것입니다. 해바라기와 쌍둥이 해바라기는 먹힐 때 태양을 떨어뜨립니다!\n챕터 제작자: MirteorShower\n\n\n\n\n\n\n\n\n\n\n\n\n\n\n\n\n\n\n\n\n",
	"102CustomIZ1-1": "<size=18>시간의 잔디밭 1-1\n\n\n\n\n\n\n\n\n\n\n\n\n\n\n\n\n\n\n\n비록 퓨전 세계에 있지만, 간단한 것부터 시작해 봅시다.\n오직 바닐라 식물과 좀비들만 등장하는 이 레벨을 깰 수 있을까요?\n\n\n\n\n\n\n\n\n\n\n\n\n\n\n\n\n\n\n\n\n",
	"103CustomIZ1-2": "<size=18>시간의 잔디밭 1-2\n<size=12><alpha=#03>최적 해법: 1200 태양 남기기\n<size=6><alpha=#00>awa\n<size=18><alpha=#FF>\n\n\n\n\n\n\n\n\n\n\n\n\n\n\n\n\n\n난이도가 갑자기 너무 어려워지지는 않았길 바랍니다.\n좀비들의 능력과 특징에 대해 더 알고 싶다면 도감을 확인해 보세요.\n참고: 오직 해바라기와 쌍둥이 해바라기만 먹힐 때 태양을 떨어뜨립니다.\n\n\n\n\n\n\n\n\n\n\n\n\n\n\n\n\n\n\n\n\n",
	"104CustomIZ1-3教程": "<size=18>시간의 잔디밭 1-3 튜토리얼: 큰태양 버섯\n\n\n\n\n\n\n\n\n\n\n\n\n\n\n\n\n\n\n\n이곳은 튜토리얼 레벨입니다! 튜토리얼 레벨에서는 태양이 아주 넉넉하며, 좀비를 원하는 곳 어디든 배치할 수 있습니다!\n3번째 라인의 화분에 심어진 식물은 큰태양 버섯입니다. 이 식물은 5×5 범위 내에 떨어진 태양을 흡수합니다. 그리고 한 번 흡수한 태양은 돌려주지 않습니다.\n큰태양 버섯을 발견하면 태양을 놓치지 않도록 최우선적으로 제거하세요!\n\n\n\n\n\n\n\n\n\n\n\n\n\n\n\n\n\n\n\n\n",
	"105CustomIZ1-3": "<size=18>시간의 잔디밭 1-3\n<size=12><alpha=#03>최적 해법: 950 태양 남기기\n<size=6><alpha=#00>awa\n<size=18><alpha=#FF>\n\n\n\n\n\n\n\n\n\n\n\n\n\n\n\n\n\n이 레벨에서는 두 종류의 장대 좀비를 사용할 수 있습니다. 75 태양짜리는 저렴하지만, 체력이 종잇장처럼 약합니다.\n팁: 일시정지 메뉴에서 식물과 좀비의 체력 표시를 켜고 끌 수 있습니다. PC에서는 Q 또는 W를 눌러서 확인할 수도 있습니다.\n\n\n\n\n\n\n\n\n\n\n\n\n\n\n\n\n\n\n\n\n",
	"106CustomIZ1-4": "<size=18>시간의 잔디밭 1-4\n<size=12><alpha=#03>최적 해법: 1100 태양 남기기\n<size=6><alpha=#00>awa\n<size=18><alpha=#FF>\n\n\n\n\n\n\n\n\n\n\n\n\n\n\n\n\n\n가끔은 큰태양 버섯이 태양을 훔쳐 가는 것을 막기 어려울 때도 있습니다. 너무 스트레스받지 마세요. 조금 잃어도 괜찮습니다. 완벽할 필요는 없으니까요.\n참고로, 좀보타니 좀비들이 멀리서 공격할 수 있더라도 때로는 식물 바로 앞에 배치하는 것이 더 효과적일 수 있습니다.\n진행이 막혔나요? 난이도를 높이면 좀비들이 받는 대미지를 줄일 수 있습니다. (하지만 너무 의존하지는 마세요!)\n\n\n\n\n\n\n\n\n\n\n\n\n\n\n\n\n\n\n\n\n",
	"107CustomIZ1-5-1": "<size=18>시간의 잔디밭 1-5-1\n<size=12><alpha=#03>최적 해법: 1025 태양 남기기\n<size=6><alpha=#00>awa\n<size=18><alpha=#FF>\n\n\n\n\n\n\n\n\n\n\n\n\n\n\n\n\n\n1-5에 오신 것을 환영합니다! 이번에는 여러 단계로 구성된 레벨입니다.\n맨 오른쪽의 기가 메카 호두 위에 좀보타니 좀비들을 배치해 보세요. 자동으로 공격을 시작할 것입니다.\n라인이 정리되면, 장대 좀비를 배치하여 뇌를 차지하세요. (메인 메뉴에서 배속 기능을 켤 수 있습니다.)\n\n\n\n\n\n\n\n\n\n\n\n\n\n\n\n\n\n\n\n\n",
	"108CustomIZ1-5-2": "<size=18>시간의 잔디밭 1-5-2\n<size=12><alpha=#03>최적 해법: 1075 태양 남기기\n<size=6><alpha=#00>awa\n<size=18><alpha=#FF>\n\n\n\n\n\n\n\n\n\n\n\n\n\n\n\n\n\n오른쪽에 지뢰 호박 한 줄을 추가했습니다. 이제 방어형 좀보타니 좀비들을 배치할 공간이 생겼을 거예요.\n같은 타일에 여러 마리의 사격형 좀보타니를 겹쳐 배치하면 엄청난 화력을 낼 수 있습니다.\n팁: 모르는 식물을 발견하면 도감을 확인해 보세요. 당신이 하고 있는 PC판에서는 식물 위에 마우스를 올리고 C를 누르면 빠르게 찾아볼 수 있습니다.\n\n\n\n\n\n\n\n\n\n\n\n\n\n\n\n\n\n\n\n\n",
	"109CustomIZ1-5-3": "<size=18>시간의 잔디밭 1-5-3\n<size=12><alpha=#03>최적 해법: 900 태양 남기기\n<size=6><alpha=#00>awa\n<size=18><alpha=#FF>\n\n\n\n\n\n\n\n\n\n\n\n\n\n\n\n\n\n좀보타니 좀비들을 현명하게 조합하여 식물 방어선을 밀어버리세요!\n그리고 잊지 마세요, 큰태양 버섯을 가장 먼저 제거해야 합니다.\n팁: 왼쪽 하단의 슬로우 모드 버튼을 누르면 (PC에서는 키보드 3) 속도가 느려져 여러 마리의 좀비를 더 쉽게 배치할 수 있습니다.\n\n\n\n\n\n\n\n\n\n\n\n\n\n\n\n\n\n\n\n\n",
	"110CustomIZ1-6教程": "<size=18>시간의 잔디밭 1-6 튜토리얼: 태양 스쿼시 1\n\n\n\n\n\n\n\n\n\n\n\n\n\n\n\n\n\n\n\n공격한 후, 태양 스쿼시는 태양을 자동으로 소모하여 부활합니다.\n부활 횟수가 늘어날수록 더 많은 태양이 필요합니다. 태양이 충분하지 않으면 영구적으로 죽게 됩니다.\n태양이 50 미만일 때 공격을 유도하는 것을 권장합니다. 그러면 부활하지 않으며 추가 비용도 들지 않습니다.\n또한, 원거리 공격은 태양 스쿼시의 부활을 막지 못합니다. 1번째 라인에 사격형 좀보타니를 배치하여 어떻게 작동하는지 확인해 보세요.\n\n\n\n\n\n\n\n\n\n\n\n\n\n\n\n\n\n\n\n\n",
	"111CustomIZ1-6": "<size=18>시간의 잔디밭 1-6\n<size=12><alpha=#03>최적 해법: 850 태양 남기기\n<size=6><alpha=#00>awa\n<size=18><alpha=#FF>\n\n\n\n\n\n\n\n\n\n\n\n\n\n\n\n\n\n태양 스쿼시의 공격을 유도하기 전에 최대한 많은 태양을 사용하세요.\n물론 부활 한계치를 높이기 위해 의도적으로 태양을 희생할 수도 있습니다. 다만 너무 과하게 사용하지는 마세요.\n팁: 필요한 순간에 좀비를 빠르게 배치할 수 있도록 슬로우 모드를 사용하는 것을 잊지 마세요.\n\n\n\n\n\n\n\n\n\n\n\n\n\n\n\n\n\n\n\n\n",
	"112CustomIZ1-7教程": "<size=18>시간의 잔디밭 1-7 튜토리얼: 태양 스쿼시 2\n\n\n\n\n\n\n\n\n\n\n\n\n\n\n\n\n\n\n\n태양 스쿼시가 이미 식물이 있는 타일에 내려앉으면, 태양이 충분하더라도 부활하지 않습니다. (3번째 라인을 확인하세요.)\n잔디밭에 아직 몇몇 태양 스쿼시가 남아 있습니다. 여러분의 선택 창에 있는 좀비들을 사용해 최대한 효율적으로 대처해 보세요.\n(튜토리얼을 건너뛰고 싶나요? 1열에 좀비들을 배치해 뇌를 바로 먹으면 됩니다.)\n\n\n\n\n\n\n\n\n\n\n\n\n\n\n\n\n\n\n\n\n",
	"113CustomIZ1-7": "<size=18>시간의 잔디밭 1-7\n<size=12><alpha=#03>최적 해법: 775 태양 남기기\n<size=6><alpha=#00>awa\n<size=18><alpha=#FF>\n\n\n\n\n\n\n\n\n\n\n\n\n\n\n\n\n\n태양 스쿼시가 훨씬 더 많이 나옵니다! 준비가 되셨길 바랍니다. 1-7 레벨의 기술들을 잘 활용할 수 있다면, 태양에 대해 그렇게 많이 걱정하지 않아도 될 거예요...\n\n\n\n\n\n\n\n\n\n\n\n\n\n\n\n\n\n\n\n\n",
	"114CustomIZ1-8": "<size=18>시간의 잔디밭 1-8\n<size=12><alpha=#03>최적 해법: 925 태양 남기기\n<size=6><alpha=#00>awa\n<size=18><alpha=#FF>\n\n\n\n\n\n\n\n\n\n\n\n\n\n\n\n\n\n좋은 소식: 이 방어선은 전부 해바라기와 그 조합 식물들로 이루어져 있습니다.\n나쁜 소식: 큰태양 버섯과 태양 스쿼시도 함께 등장합니다.\n긍정적인 면은, 새로운 좀비인 '치킨 좀키'를 사용할 수 있다는 점입니다. 매우 빠르기 때문에 스쿼시의 공격을 유도하기에 아주 좋습니다.\n팁: 이 레벨은 어느 정도의 실수는 허용됩니다. 큰태양 버섯이나 태양 스쿼시에게 태양을 조금 낭비하더라도 충분히 이길 수 있습니다.\n\n\n\n\n\n\n\n\n\n\n\n\n\n\n\n\n\n\n\n\n",
	"115CustomIZ1-9": "<size=18>시간의 잔디밭 1-9\n<size=12><alpha=#03>최적 해법: 400 태양 남기기\n<size=6><alpha=#00>awa\n<size=18><alpha=#FF>\n\n\n\n\n\n\n\n\n\n\n\n\n\n\n\n\n\n체리슈터 좀비가 발사하는 폭발성 체리는 범위 대미지를 입힙니다. 이를 이용해 2번째와 4번째 라인을 공략해 보세요.\n체리가 정확한 위치에서 터지게 하려면, 다른 좀비들을 먼저 보내 방어선을 조금 갉아먹어 둘 필요가 있습니다.\n(이전에 체리슈터 좀비를 본 적이 있겠지만, 이번에는 폭발 위치가 훨씬 더 중요합니다.)\n\n\n\n\n\n\n\n\n\n\n\n\n\n\n\n\n\n\n\n\n",
	"116CustomIZ1-10": "<size=18>시간의 잔디밭 1-10\n<size=12><alpha=#03>최적 해법: 575 태양 남기기\n<size=6><alpha=#00>awa\n<size=18><alpha=#FF>\n\n\n\n\n\n\n\n\n\n\n\n\n\n\n\n\n\n어라... 가운데 라인에 있는 건 체리 개틀링인가요? 지원군까지 데려왔군요!\n체리 개틀링은 체리 폭발 대미지에 면역입니다. 먼저 범위 공격을 이용해 뒤에 있는 사격형 식물들을 제거해 보세요.\n지원을 잃고 홀로 남은 체리 개틀링은 더 이상 무섭지 않습니다.\n\n\n\n\n\n\n\n\n\n\n\n\n\n\n\n\n\n\n\n\n",
	"201CustomIZ2：菇泛远影": "<size=18>제2장: 버섯 그늘\n\n\n\n\n\n\n\n\n\n\n\n\n\n\n\n\n\n\n\n제2장에 오신 것을 환영합니다! 이번에는 온갖 종류의 버섯들을 마주하고, 그들을 쓰러뜨려야 합니다.\n또한 더 복잡한 메커니즘을 가진 새로운 좀비들이 해제됩니다. 혼란스러운 부분이 있다면 잊지 말고 도감을 확인해 보세요.\n챕터 제작자: MirteorShower\n\n\n\n\n\n\n\n\n\n\n\n\n\n\n\n\n\n\n\n\n",
	"202CustomIZ2-1": "<size=18>버섯 그늘 2-1\n<size=12><alpha=#03>최적 해법: 950 태양 남기기\n<size=6><alpha=#00>awa\n<size=18><alpha=#FF>\n\n\n\n\n\n\n\n\n\n\n\n\n\n\n\n\n\n한 타일에 최대 3마리의 뻐끔 버섯이 겹쳐질 수 있습니다!\n개별적으로 보면 이전보다 조합된 모습이 그리 인상적이지 않을지 몰라도,\n세 마리가 모인다면? 그 수치는 꽤 골치 아픈 문제가 될 겁니다.<size=6>\n<size=12>심지어 종류가 섞여 있다면… 행운을 빕니다.<size=18>\n\n\n\n\n\n\n\n\n\n\n\n\n\n\n\n\n\n\n\n\n",
	"203CustomIZ2-2教程": "<size=18>버섯 그늘 2-2 튜토리얼: 겁쟁이 버섯\n\n\n\n\n\n\n\n\n\n\n\n\n\n\n\n\n\n\n\n많은 겁쟁이 버섯은 강력한 원거리 공격 능력을 갖추고 있습니다. 하지만 좀비가 주변 3×3 범위 안에 들어오면,\n겁에 질려 공격을 멈춥니다. 이 약점을 이용하려면, 먼저 인접한 라인에 좀비를 배치해 버섯들을 숨게 만든 뒤\n해당 라인에 좀비를 투입하세요. (1번째와 2번째 라인을 확인해 보세요.) 이렇게 하면 받는 대미지를 크게 줄여 훨씬 쉽게 돌파할 수 있습니다.\n\n\n\n\n\n\n\n\n\n\n\n\n\n\n\n\n\n\n\n\n",
	"204CustomIZ2-2": "<size=18>버섯 그늘 2-2\n<size=12><alpha=#03>최적 해법: 825 태양 남기기\n<size=6><alpha=#00>awa\n<size=18><alpha=#FF>\n\n\n\n\n\n\n\n\n\n\n\n\n\n\n\n\n\n승마 좀비는 이동 속도가 빠르며 돌진하는 경로에 있는 대부분의 식물을 체력에 상관없이 즉시 짓밟을 수 있습니다. 하지만 단점이 있다면,\n내구력이 그리 높지 않고 충돌 후 다시 움직이기까지 시간이 필요하다는 점입니다. 공격이 명중하기 전에 죽지 않도록 주의하세요.\n팁: 일부 겁쟁이 버섯은 독특한 방식으로 공격합니다. 자세한 내용은 도감을 확인해 보세요.\n\n\n\n\n\n\n\n\n\n\n\n\n\n\n\n\n\n\n\n\n",
	"205CustomIZ2-3": "<size=18>버섯 그늘 2-3\n<size=12><alpha=#03>최적 해법: 750 태양 남기기\n<size=6><alpha=#00>awa\n<size=18><alpha=#FF>\n\n\n\n\n\n\n\n\n\n\n\n\n\n\n\n\n\n이제 라인이 하나 더 추가되었습니다! 승리하려면 6개의 뇌를 모두 먹어야 합니다.\n새로운 버섯인 던지미 버섯이 등장합니다. 이 버섯은 근처의 꼬마 호두 버섯을 집어 들어 강력한 대미지를 주는 투사체로 발사합니다.\n주변에 꼬마 호두 버섯이 없다면 던지미 버섯은 아무것도 못 하는 낙동강 오리알 신세가 됩니다. 작은 녀석들을 먼저 제거하는 것이 현명한 선택일 수 있습니다.\n\n\n\n\n\n\n\n\n\n\n\n\n\n\n\n\n\n\n\n\n",
	"206CustomIZ2-4": "<size=18>버섯 그늘 2-4<size=12>\n<alpha=#60>(43056721 제작, MirteorShower 수정)\n<alpha=#04>최적 해법: 800 태양 남기기\n<alpha=#00>.<alpha=#FF><size=18>\n\n\n\n\n\n\n\n\n\n\n\n\n\n\n\n\n\n꼬마 호두 버섯이 너무 많다면, 오히려 던지미 버섯의 메커니즘을 역이용할 수 있습니다.\n던지미 버섯 앞에 다이아몬드 박스 좀비를 배치해 성가신 꼬마 호두 버섯들을 빠르게 제거해 보세요.\n<size=6>\n<size=15>(단점: 다이아몬드 박스 좀비 하나를 희생해야 합니다… 던지미 버섯의 공격을 유도할 더 현명한 방법을 찾아내지 못한다면 말이죠.)<size=18>\n\n\n\n\n\n\n\n\n\n\n\n\n\n\n\n\n\n\n\n\n",
	"207CustomIZ2-5-1": "<size=18>버섯 그늘 2-5-1\n<size=12><alpha=#03>최적 해법: 900 태양 남기기\n<size=6><alpha=#00>awa\n<size=14><alpha=#FF>\n\n\n\n\n\n\n\n\n\n\n\n\n\n\n\n\n\n2-5에 오신 것을 환영합니다. 이 스테이지들에서는 승마 미식축구 개틀링 좀비만 사용할 수 있습니다. 이 좀비는 모든 면에서 강력합니다.\n하지만 주의할 점이 있습니다. 말을 타고 있는 동안에는 뇌를 먹지 못합니다. 뇌를 얻기 위해서는 먼저 식물들이 말을 처치하게 하여\n기가 양동이 특전사를 소환해야 합니다.\n여전히 헷갈리시나요? 1번째, 3번째, 5번째 라인에 좀비를 배치하고 어떤 일이 일어나는지 지켜보세요.\n(파멸의 가스 버섯을 직접 사용하고 대미지 업그레이드로 강화하는 것을 잊지 마세요.)\n\n\n\n\n\n\n\n\n\n\n\n\n\n\n\n\n\n\n\n\n",
	"208CustomIZ2-5-2": "<size=18>버섯 그늘 2-5-2\n<size=12><alpha=#03>최적 해법: 550 태양 남기기\n<size=6><alpha=#00>awa\n<size=18><alpha=#FF>\n\n\n\n\n\n\n\n\n\n\n\n\n\n\n\n\n\n잘하셨습니다. 아마 눈치채셨겠지만, 일부 식물들은 TD 모드용 식물이라 태양을 사용해 수동으로 업그레이드하고 능력치를 높일 수 있습니다.\n여기서는 업그레이드가 필수적입니다. 승마 미식축구 개틀링 좀비를 말에서 떨어뜨릴 만큼 충분한 대미지를 확보하지 못하면 레벨을 클리어할 수 없습니다.\n<u>이제부터 업그레이드 가능한 모든 식물은 태양 화분으로 표시됩니다.</u> 어떤 업그레이드가 필요할지 신중하게 선택하세요.\n\n\n\n\n\n\n\n\n\n\n\n\n\n\n\n\n\n\n\n\n",
	"209CustomIZ2-5-3": "<size=18>버섯 그늘 2-5-3\n<size=12><alpha=#03>최적 해법: 1160 태양 남기기\n<size=6><alpha=#00>awa\n<size=18><alpha=#FF>\n\n\n\n\n\n\n\n\n\n\n\n\n\n\n\n\n<size=14>\n\n<size=18>초반에 업그레이드에 태양을 너무 많이 쓰면 나중에 자금이 부족해질 수 있으니 신중하게 계획하세요.\n이 레벨에서는 공격 순서가 매우 중요합니다.\n올바른 순서로 공략하면 식물의 대미지 효율을 높일 수 있고, 심지어 태양을 얻는데에도 도움이 됩니다.\n\n\n\n\n\n\n\n\n\n\n\n\n\n\n\n\n\n\n\n<size=9>\n",
	"210CustomIZ2-6教程": "<size=18>버섯 그늘 2-6 튜토리얼: 파멸 먹깨비\n\n\n\n\n\n\n\n\n\n\n\n\n\n\n\n\n\n\n\n파멸 먹깨비는 공격할 때 바로 앞에 있는 모든 식물을 파괴합니다. 식물의 종류나 숫자에 상관없이 전부 즉시 사라집니다.\n의도적으로 좀비를 먹잇감으로 던져 파멸 먹깨비의 공격을 유도하면, 녀석이 아군을 \"배신\"하게 만들어 이득을 취할 수 있습니다.\n(다만, 이 전략을 쓸 계획이라면 좀비를 한꺼번에 여러 마리 배치하지 마세요.\n파멸 버섯의 폭발은 대부분의 좀비 또한 즉시 전멸시킵니다.)\n\n\n\n\n\n\n\n\n\n\n\n\n\n\n\n\n\n\n\n\n",
	"211CustomIZ2-6": "<size=18>버섯 그늘 2-6<size=12>\n<alpha=#60>(43056721 제작, MirteorShower 수정)\n<alpha=#04>최적 해법: 800 태양 남기기\n<alpha=#00>.<alpha=#FF><size=18>\n\n\n\n\n\n\n\n\n\n\n\n\n\n\n\n\n\n파멸 버섯 계열은 수명이 짧을지 모르지만, 그 짧은 순간에 압도적인 힘을 뿜어냅니다.\n식물들은 조합을 통해 이 에너지를 안정화했지만, 여전히 휘발성이 강합니다.\n파멸 먹깨비의 파괴적인 힘을 영리하게 이용해 승리를 향한 길을 개척하세요.\n\n\n\n\n\n\n\n\n\n\n\n\n\n\n\n\n\n\n\n\n",
	"212CustomIZ2-7教程": "<size=18>버섯 그늘 2-7 튜토리얼: 파멸 스쿼시\n\n\n\n\n\n\n\n\n\n\n\n\n\n\n\n\n\n\n\n파멸 스쿼시가 착지하면, 충돌한 타일에 파멸 버섯의 폭발을 일으킵니다.\n이 폭발은 식물들도 즉시 파괴합니다. (1번째 라인을 확인해 보세요.) 파멸 먹깨비와 달리, 파멸 스쿼시는 착지 지점을 조절할 수 있어\n폭발을 훨씬 유연하게 활용할 수 있습니다. 이제 인벤토리에 표시된 순서대로\n3번째, 4번째, 5번째, 여섯 번째 라인의 6열에 좀비들을 배치하세요. 파멸 스쿼시가 자동으로 저 불꽃 키다리 호두들을 날려버릴 것입니다.\n\n\n\n\n\n\n\n\n\n\n\n\n\n\n\n\n\n\n\n\n",
	"213CustomIZ2-7": "<size=18>버섯 그늘 2-7\n<size=12><alpha=#02>최적 해법: 700 태양 남기기\n<size=6><alpha=#00>awa\n<size=18><alpha=#FF>\n\n\n\n\n\n\n\n\n\n\n\n\n\n\n\n\n\n새로운 좀비가 해제되었습니다: 장대 챔피언 좀비. 이 좀비는 매우 멀리 점프하며, 충분한 도움닫기 거리가 확보되면 키다리 호두조차 무시하고 넘을 수 있습니다.\n키다리 호두를 넘기고 싶다면, 좀비를 더 오른쪽에 배치하여 충분한 주로를 확보해 주세요.\n참고: 도움닫기 거리는 키다리 호두를 넘을 수 있는지 여부만 결정할 뿐, 점프 거리 자체를 변화시키지는 않습니다.\n\n\n\n\n\n\n\n\n\n\n\n\n\n\n\n\n\n\n\n\n",
	"214CustomIZ2-8教程": "<size=18>버섯 그늘 2-8 튜토리얼: 저주 버섯 & 매혹 호박\n<size=12><alpha=#40>이 튜토리얼을 건너뛰려면 가장 왼쪽 열에 좀비를 배치하세요.\n<alpha=#FF><size=0>\n<size=18>\n\n\n\n\n\n\n\n\n\n\n\n\n\n\n\n\n\n좀비가 저주 버섯을 먹으면, 죽을 때 폭발하여 식물들까지 파괴하는 매혹된 좀비로 변합니다. (2번째 라인을 확인해 보세요.)\n먼저 좀비를 보내 저주 버섯을 먹게 하세요. 매혹된 좀비가 매혹 호박에 도달하면 그 자리에 고정됩니다.\n그다음 다른 좀비를 보내 녀석을 처치하고 폭발을 일으켜 식물들을 파괴하세요.\n5번째 라인 뒤쪽에 또 다른 저주 버섯이 있습니다. 이것을 이용해 5열에 있는 불꽃 호두를 날려버릴 수 있을까요?\n\n\n\n\n\n\n\n\n\n\n\n\n\n\n\n\n\n\n\n<size=10>\n",
	"215CustomIZ2-8": "<size=18>버섯 그늘 2-8<size=12>\n<alpha=#60>(43056721 제작, MirteorShower 수정)\n<alpha=#04>최적 해법: 625 태양 남기기\n<alpha=#00>.<alpha=#FF><size=18>\n\n\n\n\n\n\n\n\n\n\n\n\n\n\n\n\n\n다양한 파멸 버섯 조합들이 섞여 있는 혼돈의 스테이지입니다! <alpha=#80><s>아군 사격</s><alpha=#FF>을 영리하게 이용하면 공략이 훨씬 쉬워집니다.\n여기에는 얼음 키다리 호두 좀비도 등장합니다. 이들은 둔화와 빙결에 면역이므로, 얼음 식물들은 이들에게 식은 죽 먹기입니다.\n팁: 어떻게 시작해야 할지 모르겠나요? 3번째 라인에 승마 미식축구 개틀링 좀비를 배치해 보세요.\n\n\n\n\n\n\n\n\n\n\n\n\n\n\n\n\n\n\n\n\n",
	"216CustomIZ2-9": "<size=18>버섯 그늘 2-9\n<size=12><alpha=#03>최적 해법: 475 태양 남기기\n<size=6><alpha=#00>awa\n<size=18><alpha=#FF>\n\n\n\n\n\n\n\n\n\n\n\n\n\n\n\n\n\n댄서 좀비는 점프한 후 자신의 주변에 네 명의 백댄서 장대 좀비를 소환합니다.\n강력한 기동성과 소환 능력을 갖췄지만, 비용이 조금 비싼 편입니다.\n빠른 학습을 돕기 위해 잔디밭 위에 많은 <u>발광 화분</u>을 표시해 두었습니다.\n댄서 좀비가 그 화분 위의 식물들을 뛰어넘게 해보세요. 순서만 제대로 맞춘다면 이 레벨은 금방 해결됩니다.\n\n\n\n\n\n\n\n\n\n\n\n\n\n\n\n\n\n\n\n\n",
	"217CustomIZ2-10": "<size=18>버섯 그늘 2-10\n<size=12><alpha=#02>최적 해법: 625 태양 남기기\n<size=6><alpha=#00>awa\n<size=18><alpha=#FF>\n\n\n\n\n\n\n\n\n\n\n\n\n\n\n\n\n\n오디세이 식물들이 돌아왔습니다. 이번에는 무려 두 배나 더 많군요.\n좀비들의 힘만으로는 돌파할 수 없습니다. 파멸 버섯 조합을 영리하게 활용하여 식물들을 압도해야 합니다.\n2-9처럼 이 레벨에도 발광 화분 힌트가 있지만... 배치가 완전히 무의미해 보이는데요...?\n<i>' 버섯 그늘 - 빛이 형태를 드러내는 곳.' - 아마도 데이브 자(Dave Tzu)가\n<size=6>\n<size=18>\n\n\n\n\n\n\n\n\n\n\n\n\n\n\n\n\n\n\n",
	"301CustomIZ3：推波助澜": "<size=18>3장: 흐름 만들기\n<size=9>\n<size=18>\n\n\n\n\n\n\n\n\n\n\n\n\n\n\n\n\n\n식물들이 잔디밭을 버리고 방어선을 수영장으로 옮긴 것 같습니다.\n대부분의 좀비는 수로 라인에 배치할 수 없지만, 일반 좀비, 꼬깔콘 좀비, 양동이 좀비는 지형 제한을 무시합니다.\n(곧 수중 전투를 위해 특별히 제작된 좀비들을 잠금 해제하게 될 것입니다.)\n챕터 제작자: MirteorShower\n\n\n\n\n\n\n\n\n\n\n\n\n\n\n\n\n\n\n\n<size=9>\n",
	"302CustomIZ3-1": "<size=18>흐름 만들기 3-1<size=12>\n<alpha=#60>\n<alpha=#04>최적 해법: 850 태양 남기기\n<alpha=#00>(43056721 제작, MirteorShower 수정)<alpha=#FF><size=18>\n\n\n\n\n\n\n\n\n\n\n\n\n\n\n\n\n\n잠수 좀비는 물속에 있는 동안 직선으로 발사되는 식물들의 표적이 되지 않습니다. 장거리 수중 침투에 완벽하죠.\n또한 스쿼시 호두를 상대하기에도 아주 좋습니다. 4번째 라인에 직접 하나를 배치하고 어떤 일이 일어나는지 확인해 보세요.\n팁: 인게임 속도가 빠르다면 스쿼시 호두가 잠수 좀비를 공격할 수도 있습니다. 만약 그런 일이 발생하면 일반 속도로 전환하세요.\n\n\n\n\n\n\n\n\n\n\n\n\n\n\n\n\n\n\n\n\n",
	"303CustomIZ3-2教程": "<size=18>흐름 만들기 3-2 튜토리얼: 연불꽃\n<size=12>이 튜토리얼을 건너뛰려면 가장 왼쪽 열에 좀비를 배치하세요.\n<alpha=#FF><size=6>\n<size=18>\n\n\n\n\n\n\n\n\n\n\n\n\n\n\n\n\n\n연불꽃은 투사체를 6번 흡수하거나 체력이 0이 되면 죽으면서 비료 주머니를 떨어뜨립니다. (퍼즐 모드에서는 태양을 떨어뜨리지 않습니다.)\n좀비로 플레이하고 있지만, 비료를 영리하게 사용하면 식물 방어선을 무너뜨리는 데 도움이 됩니다. 예를 들어:\n<u>가스 버섯 + 비료 = 우울 버섯 (사거리 감소).</u>\n<u>잿빛 삼발슈터 + 비료 = 일반 삼발슈터 (피해량 절반).</u>\n\n\n\n\n\n\n\n\n\n\n\n\n\n\n\n\n\n\n\n<size=18>\n",
	"304CustomIZ3-2": "<size=18>흐름 만들기 3-2<size=12>\n<alpha=#60>\n<alpha=#04>최적 해법: 775 태양 남기기\n<alpha=#00>>(43056721 제작, MirteorShower 수정)<alpha=#FF><size=18>\n\n\n\n\n\n\n\n\n\n\n\n\n\n\n\n\n\n스쿼시 좀비는 체력을 무시하고 대부분의 식물을 즉시 짓뭉갭니다. 질기고 체력이 높은 목표물인가요? 그냥 스쿼시가 처리하게 두세요.\n튜토리얼에서 기본적인 비료 활용 팁을 배우셨겠지만, 비료는 먹깨비의 소화 속도를 높이는 등의 일도 할 수 있습니다.\n하지만… 왜 먹깨비가 더 빨리 소화하기를 바라겠어요? 우리한테는 소화가 느린 편이 더 좋지 않을까요?\n\n\n\n\n\n\n\n\n\n\n\n\n\n\n\n\n\n\n\n\n",
	"305CustomIZ3-3教程": "<size=18>흐름 만들기 3-3 튜토리얼: 캣 스쿼시\n<size=12>이 튜토리얼을 건너뛰려면 가장 왼쪽 열에 좀비를 배치하세요.\n<alpha=#FF><size=6>\n<size=18>\n\n\n\n\n\n\n\n\n\n\n\n\n\n\n\n\n\n캣 스쿼시는 짓뭉갠 좀비 수에 따라 스쿼시 씨앗 패킷을 떨어뜨립니다.\n이 스쿼시들을 특정 식물과 조합하여 식물을 \"너프\"할 수 있습니다. 예를 들어:\n<u>호두 + 스쿼시 = 스쿼시 호두 (허술한 방어).</u>   <u>최면 버섯 + 스쿼시 = 최면 스쿼시 (피하기 가능).</u>\n비교를 위해, 1번째 라인과 2번째 라인의 여섯 번째 열에 미식축구 호두 좀비를 배치해 보세요.\n2번째 라인의 좀비는 살아남아 뇌를 먹지만, 1번째 라인의 좀비는 그러지 못합니다.\n\n\n\n\n\n\n\n\n\n\n\n\n\n\n\n\n\n\n\n<size=18>\n",
	"306CustomIZ3-3": "<size=18>흐름 만들기 3-3<size=12>\n<alpha=#60>(Flames on the tree stump 제작, MirteorShower 수정)\n<alpha=#04>최적 해법: 850 태양 남기기\n<alpha=#00>.<alpha=#FF><size=18>\n\n\n\n\n\n\n\n\n\n\n\n\n\n\n\n\n\n<size=9>\n<size=18>고래 라이더 예티는 물이 있는 라인에만 배치할 수 있지만, 굉장히 먼 거리(네 타일!)를\n뛰어넘은 뒤 뒤돌아서 식물들을 후방에서 공격합니다.\n어떤 식물에 스쿼시를 조합할지 고민되시나요? 맵에 있는 기본 식물들을 고려해 보세요. (해바라기 제외)\n\n\n\n\n\n\n\n\n\n\n\n\n\n\n\n\n\n\n\n\n<size=9>\n",
	"307CustomIZ3-4": "<size=18>흐름 만들기 3-4\n<size=12><alpha=#03>최적 해법: 800 태양 남기기\n<size=6><alpha=#00>awa\n<size=18><alpha=#FF>\n\n\n\n\n\n\n\n\n\n\n\n\n\n\n\n\n\n연불꽃은 비료를 제공할 뿐만 아니라 식물의 투사체를 흡수하여 좀비가 받는 피해를 줄여줄 수도 있습니다.\n이번 레벨에서는 일부 비료가 남을 수도 있지만, 연불꽃을 적절히 사용해 피해를 흡수하는 것 또한 스테이지를 클리어하는 데 도움이 될 수 있습니다!\n팁: 식물 체력 표시를 켜서 연불꽃이 투사체를 몇 번 더 흡수할 수 있는지 확인해 보세요 (파란색 숫자).<size=18>\n\n\n\n\n\n\n\n\n\n\n\n\n\n\n\n\n\n\n\n\n",
	"308CustomIZ3-5-1": "<size=18>흐름 만들기 3-5-1\n<size=12><alpha=#00>최적 해법: 950 태양 남기기\n<size=6><alpha=#00>awa\n<size=18><alpha=#FF>\n\n\n\n\n\n\n\n\n\n\n\n\n\n\n\n\n\n좀비들이 당신의 플레이가 형편없다고 생각합니다! 그들은 스스로의 힘에 의지하기로 결정한 것 같군요.\n아무것도 하지 마세요. 승리하세요. (네, 다음 두 레벨도 역시 자동 진행 스테이지입니다).\n그래도 혹시 모를 상황을 대비해... 혹은 지켜보는 게 지루해서 빨리 넘기고 싶을 때를 위해 몇 가지 예비 유닛을 준비해 두었습니다.<size=18>\n\n\n\n\n\n\n\n\n\n\n\n\n\n\n\n\n\n\n\n\n",
	"309CustomIZ3-5-2": "<size=18>흐름 만들기 3-5-2<size=12>\n<alpha=#60>(MirteorShower 제작)\n<alpha=#00>최적 해법: 0 태양 남기기\n<alpha=#00>.<alpha=#FF><size=18>\n이 좀비를 자세히 지켜보세요 →<alpha=#00>-----------------------------------\n<alpha=#FF>그는 한 번에 다섯 개의 뇌를 먹는 챌린지에 도전 중입니다. 과연 성공할 수 있을까요?<alpha=#00>---------------------------------------------\n\n\n\n\n\n\n\n\n\n\n\n\n\n\n\n<alpha=#FF><size=16>기본 정보: 자동 스테이지, 배속 가능, 약간의 식물 중첩\n테스트 결과, 좀비와 식물 사이의 애니메이션 차이(불가피함)로 인해 해당 좀비가 다섯 개의 뇌를 모두 먹을 확률은 약 70% 정도입니다.\n만약 그가 다섯 개의 뇌를 모두 먹는 데 실패한다면, 씨앗 슬롯에 있는 가르강튀아를 사용해 남은 물 라인을 처리하거나,\n단순히 레벨을 재시도하여 그에게 한 번 더 기회를 주면 됩니다.\n<size=18>\n\n\n\n\n\n\n\n\n\n\n\n\n\n\n\n\n\n\n\n",
	"310CustomIZ3-5-3": "<size=18>흐름 만들기 3-5-3<size=12>\n<alpha=#60>(43056721 제작)\n<alpha=#00>최적 해법: 800 태양 남기기\n<alpha=#00>.<alpha=#FF><size=18>\n\n\n\n\n\n\n\n\n\n\n\n\n\n\n\n\n\n기본 정보: 자동 스테이지, 배속 미지원, 일반 속도에서 100% 클리어 가능\n배속을 켤 경우 자동으로 클리어되지 않을 수 있으니,\n게임이 일반 속도로 실행 중인지 확인해 주세요 (전체 실행 시간은 약 십 분 정도입니다).\n팁: 기다림이 너무 길다고 느껴진다면, 좀비를 직접 배치하여 레벨을 건너뛸 수 있습니다.\n\n\n\n\n\n\n\n\n\n\n\n\n\n\n\n\n\n\n\n\n",
	"311CustomIZ3-6教程": "<size=18>흐름 만들기 3-6 튜토리얼: 얼음 & 불꽃 주입\n\n\n\n\n\n\n\n\n\n\n\n\n\n\n\n\n\n\n\n얼음/불꽃 옥수수 대포는 폭발에 휘말린 식물을 얼음 버섯이나 할라페뇨와 조합시킵니다. 이를 이용해 식물 방어선을 약화시키세요:\n<u>뻐끔 버섯 + 얼음 버섯 = 꼬마 얼음 버섯/<u> <u>삼발슈터 + 두 개의 할라페뇨 = 타버린 삼발슈터</u>\n(더 많은 조합이 존재하지만, 공간 문제로 생략합니다)\n<alpha=#FF>4번째와 5번째 라인은 미니 테스트입니다. 제대로 조합했다면, 이 두 라인에는 총 4 마리의 일반 좀비만 있으면 충분합니다.\n\n\n\n\n\n\n\n\n\n\n\n\n\n\n\n\n\n\n\n\n",
	"312CustomIZ3-6": "<size=18>흐름 만들기 3-6\n<size=12><alpha=#03>최적 해법: 800 태양 남기기\n<size=6><alpha=#00>awa\n<size=18><alpha=#FF>\n\n\n\n\n\n\n\n\n\n\n\n\n\n\n\n\n\n불꽃 옥수수 대포로 식물을 공격하기 전에 신중히 생각하세요. 대부분의 식물은 할라페뇨와 조합된 후 실제로 더 강해집니다.\n이번 레벨에는 메카 치킨 좀비도 등장합니다. 이 좀비는 체력을 무시하고 수중 라인의 식물 하나를 짓뭉갠 뒤, 근처 땅에다 임프를 발사합니다.\n팁: 화면의 맨 왼쪽을 탭하면 대포 조준을 취소할 수 있습니다.<size=18>\n\n\n\n\n\n\n\n\n\n\n\n\n\n\n\n\n\n\n\n\n",
	"313CustomIZ3-7教程": "<size=18>흐름 만들기 3-7 튜토리얼: 얼음과 불꽃의 충돌\n\n\n\n\n\n\n\n\n\n\n\n\n\n\n\n\n\n\n\n얼음과 불꽃 식물은 둘 다 강력하지만, 이들을 조합하면 서로의 효과를 상쇄시킵니다.\n1번째 라인의 불꽃 가스 버섯은 2번째 라인의 일반 가스 버섯보다 강해 보이지만, 얼음과 불꽃의 충돌 때문에 실제로는 더 적은 총 피해를 입힙니다.\n<alpha=#FF>4번째와 5번째 라인을 위한 미니 테스트: 제대로 조합한다면 두 뇌를 모두 먹는 데 <u>총 2마리의 미식축구 좀비</u>만 있으면 충분합니다.\n\n\n\n\n\n\n\n\n\n\n\n\n\n\n\n\n\n\n\n\n",
	"315CustomIZ3-8": "<<size=18>흐름 만들기 3-8<size=12>\n<alpha=#60>(Flames on the tree stump 제작, MirteorShower 수정)\n<alpha=#04>최적 해법: 625 태양 남기기\n<alpha=#00>.<alpha=#FF><size=18>\n\n\n\n\n\n\n\n\n\n\n\n\n\n\n\n\n\n스파이시 스쿼시 좀비는 얼어붙지 않는 한 한 라인 전체를 즉시 쓸어버릴 수 있습니다. (자세한 내용은 도감을 참조하세요)\n<alpha=#FF>따뜻하게 유지하세요. 비료와 얼음-불꽃 충돌을 이용해 이 좀비가 둔화 상태가 되는걸 방지해야 합니다.\n팁: 막혔을 때는 아래쪽 육지 라인의 발광 화분 위에 있는 식물들을 자세히 살펴보세요.\n\n\n\n\n\n\n\n\n\n\n\n\n\n\n\n\n\n\n\n\n",
	"316CustomIZ3-9": "<size=18>흐름 만들기 3-9\n<size=12><alpha=#03>최적 해법: 475 태양 남기기\n<size=6><alpha=#00>awa\n<size=18><alpha=#FF>\n\n\n\n\n\n\n\n\n\n\n\n\n\n\n\n\n\n좋습니다, 이제 식물들이 진지하게 나옵니다. 길 양옆을 따라 수많은 마법 양파 토끼를 심어 두었군요.\n당신의 좀비들은 많은 번개를 견뎌낼 수 없습니다. 하지만 오직 그들의 \"대장\"만이 5×5 범위로 공격할 수 있습니다. 그러니…\n마법 양파 토끼를 탭하여 대장으로 만드세요. 그들은 대장의 5×5 영역 안에 있는 좀비들만 공격합니다.</u><size=18>\n\n\n\n\n\n\n\n\n\n\n\n\n\n\n\n\n\n\n\n\n",
	"317CustomIZ3-10": "<size=18>흐름 만들기 3-10\n<size=12><alpha=#03>최적 해법: 600 태양 남기기\n<size=6><alpha=#00>awa\n<size=18><alpha=#FF>\n\n\n\n\n\n\n\n\n\n\n\n\n\n\n\n\n\n어라... 뭔가 잘못되었습니다. 지난 레벨에서도 마법 양파 토끼들이 이렇게 배치되어 있었나요?\n누구를 대장으로 선택하든, 그들의 공격 범위가 항상 2번째와 5번째 라인을 덮고 있습니다. 그럴 리가 없는데...\n<i>규칙을 깨세요. 조합해서 승리하세요. - 아마도 데이브 무가<size=18>\n\n\n\n\n\n\n\n\n\n\n\n\n\n\n\n\n\n\n\n\n",
	"401CustomIZ4：磁荧流转": "<size=18>챕터 4: 극성 전환\n\n\n\n\n\n\n\n\n\n\n\n\n\n\n\n\n\n\n\n안개 챕터에 오신 것을 환영합니다! 식물 배치가 더욱 복잡해질 것이니 신중을 기하세요!\n이 챕터에서는 더 유연하고 새로운 좀비 메커니즘들도 도입됩니다.\n이후 레벨들을 진행하며 이를 점차 발견하고 사용하는 법을 배우게 될 것입니다. 행운을 빕니다!\n\n\n\n\n\n\n\n\n\n\n\n\n\n\n\n\n\n\n\n\n",
	"402CustomIZ4-1教程": "<size=18>챕터 4: 극성 전환 4-1 튜토리얼: \"빛 시스템\"\n<size=335>\n<size=18>\"빛 시스템\"은 Fusion의 핵심 메커니즘입니다. 많은 빛 식물들이 \"빛 레벨\"에 따라 보너스를 얻습니다:\n6번째 라인의 식물들은 \"빛 레벨\"에 의해 크게 강화되지만, 이것이 없으면 매우 약해집니다.\n1번째 라인에 줄지어 있는 식물들은 \"빛 레벨\"을 제공합니다. 실전에서는 이들을 최우선적으로 공략하세요.\n<alpha=#30><size=12>(정확한 세부 사항은 도감을 확인하세요)\n<size=350>\n",
	"403CustomIZ4-1": "<size=18>극성 전환 4-1\n<size=12><alpha=#03>최적 해법: 825 태양 남기기\n<size=330><alpha=#00>\n<size=18><alpha=#FF>한 가지 더: 이 챕터부터는 식물 배치에 호박과 공중 식물들이 포함됩니다.....\n하지만 걱정할 것 없습니다. 일부 호박은 화려해 보일 수 있지만, 그저 보여주기용일 뿐입니다.\n<size=18>예를 들어, 이 레벨의 화려한 호박들은 기존의 호박과 똑같이 작동합니다.\n<size=360>\n",
	"404CustomIZ4-2教程": "<size=18>극성 전환 4-2 튜토리얼: 풍선 좀비\n\n\n\n\n\n\n\n\n\n\n\n\n\n\n\n\n\n\n\n풍선 좀비는 대부분의 식물을 무시하고 그 위를 날아갈 수 있으며, 저지하지 않으면 방해받지 않고 집까지 도달합니다 (1번째 라인 참조).\n하지만 선인장과 같은 대공 식물들은 여전히 그들을 공격할 수 있습니다. 일반 풍선은 단 한 번의 타격으로 터집니다 (2~4번째 라인 참조).\n선인장 외에도 일부 다른 식물들 역시 풍선 좀비에게 대미지를 줄 수 있습니다 (예: 5번째 라인의 추운 버섯, 6번째 라인의 토치위드).\n\n\n\n\n\n\n\n\n\n\n\n\n\n\n\n\n\n\n\n\n",
	"405CustomIZ4-2": "<size=18>극성 전환 4-2<size=12>\n<alpha=#60>(Xiaodong plays well의 도움으로 제작된 레벨)\n<alpha=#04>최적 해법: 750 태양 남기기\n<alpha=#FF><size=330>\n<size=18>양동이슈콥터 좀비는 풍선이 터지지 않고 일부 대공 공격을 견뎌낼 수 있는 풍선 좀비의 변종입니다.\n하지만 선인장 호두로 여전히 저지할 수 있습니다. 비록 도중에 격추되는 것이 항상 나쁜 것만은 아니지만요.<alpha=#FF>\n<size=370>\n",
	"406CustomIZ4-3教程": "<size=18>극성 전환 4-3 튜토리얼: 발광 먹깨비</color>\n<size=22>\n<size=72><alpha=#00>iii<alpha=#10><mark=#00FF00><alpha=#00>iiiiiiiiii</mark><alpha=#10><mark=#FFFF00><alpha=#00>iiiiiiiiiiii</mark>\n<size=18>iiiiiiiiiiii<alpha=#FF>|<--------발광 먹깨비 유인 범위-------->|\n<size=18>\n유인된 좀비의 사각지대┐<alpha=#00>iiiiiiiiiiiiiiiiiiiiiiiiiiiiiiiiiiiiiiiiiiiiiiiiiiiiiiiiiiiiiiiiiiiiiiiiiiiiiiiiiiiiiiiiiiii\n<alpha=#FF>|<---------┴--------->|<alpha=#00>iiiiiiiiiiiiiiiiiiiiiiiiiiiiiiiiiii\n<size=72><alpha=#00>iii<alpha=#10><mark=#00FF00><alpha=#00>iiiiiiiiii</mark><alpha=#10><mark=#FFFF00><alpha=#00>iiiiiiiiiiii\n<size=98>\n</mark><size=18><alpha=#FF>발광 먹깨비를 소개합니다. 이미 보셨을 수도 있겠네요. 이 식물은 소화를 마친 후 인접한 라인의 좀비를 자신의 라인으로 유인합니다.\n좀비를 먹여 라인을 전환하게 만들면, 다른 좀비가 강력한 방어선을 우회하여 후방을 타격하게 할 수 있습니다.\n라인 전환을 이용해 6번째 라인의 골드 박스 좀비를 4번째 라인으로 옮겨 뇌를 먹어보세요!\n<size=12><alpha=#40>(참고: 소화 시간을 정확히 맞출 필요는 없습니다. 이후 레벨에서 라인 전환은 항상 인접한 라인의 호두들의 도움을 받게 됩니다)\n<size=350>\n",
	"407CustomIZ4-3": "<size=18>극성 전환 4-3<size=12>\n<alpha=#60>(Xiaodong plays well의 도움으로 제작, MirteorShower 편집)\n<alpha=#04>최적 해법: 725 태양 남기기\n<alpha=#FF><size=322>\n<size=18>좀플린 비행선은 높은 체력을 가진 강력한 비행 유닛으로, 한 라인 전체에 폭격을 가할 수 있습니다.\n단점은 높은 비용과 뇌를 먹을 수 없다는 점이므로, 정말 필요한 경우에만 사용하는 것이 좋습니다.<alpha=#FF>\n<size=16>팁: 발광 먹깨비의 라인 전환을 사용할 때는 해당 라인이 비어 있는지 확인하세요 (좀비가 이미 있으면 라인 전환이 발동되지 않습니다).\n<size=362>\n",
	"408CustomIZ4-4": "<size=18>극성 전환 4-4<size=12>\n<alpha=#60>(decepticons의 도움으로 제작, MirteorShower 편집)\n<alpha=#04>최적 해법: 650 태양 남기기\n<alpha=#FF><size=322>\n<size=16>광부 좀비가 해금되었습니다! 걱정 마세요, 모든 레벨을 클리어하기 위해 자석 버섯으로 지상에 올라오는 타이밍을 완벽하게 맞출 필요는 없습니다.\n광부 좀비는 땅을 파고 후방으로 이동하며, 방해받지 않는다면 뒤에서 기습 공격을 가합니다.\n이동 중에 자석 버섯이나 광부 호박에 의해 저지당하면, 지상으로 올라와 일반적인 공격을 수행합니다.\n\t팁: 빛의 강화를 받으면, LED 자석 버섯의 유인 범위가 크게 늘어납니다. 빛이 없으면, 해당 범위(1.2타일)는 일반적인 자석 버섯의 절반 수준에 불과합니다.<alpha=#FF>\n<size=362>\n",
	"409CustomIZ4-5-1": "<size=18>극성 전환 4-5-1<size=12>\n<alpha=#60>\n<alpha=#04>최적 해법: 975 태양 남기기\n<alpha=#FF><size=320>\n<size=18>식물들이 배치를 조금 앞으로 당긴 것 같지만… 사실 큰 차이는 없습니다.\n그나저나, 빛 생산자들을 서둘러 제거하지 않는 게 좋을지도 모릅니다. 나중에 언제 결정적인 도움이 될지 모르니까요.\n<alpha=#20>일기 예보: 오늘 밤 안개<alpha=#FF>\n<size=360>\n",
	"410CustomIZ4-5-2": "<size=18>극성 전환 4-5-2<size=12>\n<alpha=#04>최적 해법: 800 태양 남기기\n<alpha=#00>최적 해법: 800 태양 남기기\n<alpha=#FF><size=320>\n<size=18>이 레벨에는 해바라기뿐입니다! 정말 쉽겠죠… 그쵸?\n일부 비행 식물들은 꽤 강력한 공격을 퍼붓는 데다, 제거할 수도 없습니다.\n물론 안개까지 끼어 상황은 더 나빠지겠네요.<alpha=#20>\n참고: 황금 해바라기는 그냥 장식입니다. 공짜 태양은 없으니 미안하네요.\n<size=360>\n",
	"411CustomIZ4-5-3": "<size=18>극성 전환 4-5-3<size=12>\n<alpha=#04>최적 해법: 775 태양 남기기\n<alpha=#00>최적 해법: 800 태양 남기기\n<alpha=#FF><size=320>\n<size=18>마지막 \"안개\" 레벨입니다! 이번에는 다양한 겁쟁이 버섯들이 가득합니다.\n겁쟁이 드론의 효과 덕분에 그들 중 누구도 먹을 수 없지만, 여전히 겁이 많은 건 여전하네요.<alpha=#FF>\n참고: 뻔뻔 버섯은 겁쟁이 드론의 영향을 받지 않습니다.\n<size=360>\n",
	"412CustomIZ4-6教程": "<size=18>극성 전환 4-6 튜토리얼: 자석 호박 & 자기장 연결\n<size=85>\n<size=15><align=left><alpha=#00>iiiiiiiiii<alpha=#FF><size=60%>예: 이 강철 호박의 대미지 배수 ↓</size>\n<alpha=#00>iiiiiiiiii<alpha=#FF>  10 (연결된 자기장 식물 수) ×\n<alpha=#00>iiiiiiiiii<alpha=#FF>2 (주변 자석 호박 수) ×\n<alpha=#00>iiiiiiiiii<alpha=#FF><u>× 2 (수중일 때) = 40 (대미지 배수)</u>\n<alpha=#45>대미지: ×1.3(양동이 좀비 속도) ×20 = 1040\n<size=72><alpha=#00>iiiiiiiiiiiiii<alpha=#60><mark=#FFFF00><alpha=#00>iiii</mark>\n<size=98>\n<align=center><size=16><alpha=#FF>자석 호박은 6초마다 주변(3×3) <u>금속 좀비*</u>에게 범위 대미지를 입힙니다. 연결된 자석 식물이 많을수록 <u>대미지*</u>가 높아집니다.\n그러니 대미지를 줄이려면 먼저 연결을 끊거나, 아니면 그냥 금속이 아닌 좀비를 사용해서 이 모든 걸 무시하세요.\n추가 조합 시에도 이 메커니즘이 계승되며, 여러 개의 자석 호박은 대미지를 중첩시킵니다(매우 빠르게 합산됩니다).\n<size=9><align=left><alpha=#60>\n*금속 좀비: 슬롯 바의 1번째 줄에 있는 모든 좀비와 좀보니가 포함됩니다(진짜예요, 하지만 누가 좀보니한테 자석 호박을 쓰겠어요 ㅋㅋㅋ)\n<alpha=#60>계산 공식은 도감을 확인하세요. 너무 걱정하실 필요는 없습니다.\n<size=345>\n",
	"413CustomIZ4-6": "<size=18>극성 전환 4-6<size=12>\n<alpha=#60>(Shuzhuangshangdehuoyan의 도움으로 제작, MirteorShower 편집)\n<alpha=#03>최적 해법: 700 태양 남기기\n<alpha=#FF><size=320>\n<size=18>스카이콩콩 좀비는 대부분의 식물을 뛰어넘을 수 있지만, 뇌를 먹는 대신 그냥 잔디밭 밖으로 뛰어 나가버립니다.\n키다리 호두에 막히거나 자석 버섯에 무장 해제되면, 바닥으로 떨어져 일반적인 공격을 시작합니다.\n(네, 그때는 뇌를 먹을 수 있습니다).\n팁: 자기장 연결을 끊으면 자석 호박의 대미지를 대폭 줄일 수 있습니다!<alpha=#FF>\n<size=360>\n",
	"414CustomIZ4-7教程": "<size=18>극성 전환 4-7 튜토리얼: 금속 물체 & 잠자석 파멸 버섯\n<size=12>\n<size=18>\n\n\n\n\n\n\n\n\n\n\n\n\n\n\n\n\n\n잠자석 파멸 버섯은 기본적으로 폭발하지 않지만, <u>특정 금속 아이템*</u>과 조합하면 폭발하여 해당 타일의 모든 식물을 파괴합니다.\n자석 버섯을 통해 금속 물체를 얻을 수 있으며, 대부분의 금속 좀보타니들도 처치 시 금속 물체을 드랍합니다.\n금속 물체을 잠자석 파멸 버섯 위로 드래그하여 폭파시키세요. 드론이나 호박을 제거하거나 자기장 연결을 끊는 데 매우 유용합니다.\n<size=12><alpha=#30>\n*특정 금속 물체: 현재는 양동이, 깜짝 상자, 크로노 코어가 해당됩니다. 후자의 두 개는… 말하자면 희귀해서, 이후 대부분의 레벨은 양동이 조합을 위주로 진행됩니다.\n\n<size=18>\n\n\n\n\n\n\n\n\n\n\n\n\n\n\n\n\n\n\n",
	"415CustomIZ4-7": "<size=18>극성 전환 4-7<size=12>\n<alpha=#60>(Xiaodong plays well의 도움으로 제작, MirteorShower 편집)\n<alpha=#04>최적 해법: 650 태양 남기기\n<alpha=#FF><size=320>\n<size=18>양동이슈터 좀비는 자석 버섯에 즉사하지 않지만, 여전히 자석 호박으로부터 대미지를 입습니다.\n또한, 양동이슈콥터 좀비는 수중에 배치할 수 있습니다. 물론 결국에는 사라지겠지만,\n전방에 상당한 대미지를 입히기 전까지는 아닙니다.\n팁: 강철 파멸 버섯에 의해 처치된 좀비는 더 많은 철 양동이를 드랍합니다.<alpha=#FF>\n<size=360>\n",
	"416CustomIZ4-8": "<size=18>극성 전환 4-8<size=12>\n<alpha=#60>(decepticons의 도움으로 제작)\n<alpha=#04>최적 해법: 500 태양 남기기\n<alpha=#FF><size=320>\n<size=18>호박 착륙장은 잔디밭 전체를 타격하는 공중 호위 지원을 동반하지만, 양동이슈콥터 좀비는 쓰러지기 전까지 한동안 공격을 견뎌낼 수 있습니다.\n이 기회를 이용해 초반 착륙 지점을 확보하고 식물 후방 라인을 무너뜨리세요.\n<alpha=#70>팁: 초반에 막힌다면 발광 스타푸르츠의 도감 항목을 확인해 보세요… 그리고 빛 공급을 약간 끊어보는 것도 방법입니다.\n<size=360>\n",
	"417CustomIZ4-9": "<size=18>극성 전환 4-9<size=12>\n<alpha=#60>(43056721의 도움으로 제작, MirteorShower 편집)\n<alpha=#04>최적 해법: 475 태양 남기기\n<alpha=#FF snowy><size=305>\n<size=18>쪽지를 발견했습니다! 이건… 지시 사항인가요?\n<size=10><b>╭————————————————————————————————————————————————————————————————————╮</b>\n    <align=left><size=15>┃  <alpha=#05><mark=#FFFFFF><alpha=#FF>1) 아무 레인에나 광부 좀비를 배치한다     2) <u>냉기 화분</u>에 도달하면, 즉시 아무 망각 플랜턴 위에 상어라이너를 배치한다</mark> ┃\n   ┃  <align=left><alpha=#05><mark=#FFFFFF><alpha=#FF>3) 망각 플랜턴의 사망 시 효과가 끝나면, 다른 광부 좀비로 이 과정을 반복한다…                                                                </mark>┃\n<align=center><size=10><b>╰————————————————————————————————————————————————————————————————————╯</b>\n<alpha=#FF><size=18>…나머지는 얼룩져서 보이지 않습니다. 아마 별로 중요한 건 아니겠죠. 아니면 중요할지도요. 너무 부담 갖지는 마세요.\n<size=345>\n",
	"418CustomIZ4-10教程": "<size=18>극성 전환 4-10 튜토리얼: 최면 자석 버섯 & 물체 공급<size=12>\n<alpha=#00>제작자: decepticons         최적 해법: 400 태양 남기기</color>\n<alpha=#00>최적 해법: 800 태양 남기기\n<alpha=#00>.<alpha=#FF><size=18>\n<size=300>\n<size=18>자석 버섯(테슬라 자석 황제 제외)이 흡수를 마치면, 동일한 자기장 시스템 내의 <color=#F2B6DB>최면 자석 버섯</color>에게 금속 물체를 전달합니다. <color=#F2B6DB>최면 자석 버섯</color>은 이 금속들을 사용해 매혹된 좀비를 생성할 수 있습니다.\n최면 먹깨비와 조합하면, <color=yellow>매혹 버섯</color> 카드 패킷을 생성해 줍니다. (1번째 레인 참조)\n<size=12>참고: 동일한 시스템 내에 <color=#F2B6DB>최면 자석 버섯</color>과 <color=#DD96E5>매혹트론 버섯</color>이 함께 존재할 경우, 금속은 항상 <color=#DD96E5>매혹트론 버섯</color>에게 먼저 전달됩니다. (4, 5, 6번째 레인 참조)\n<color=#DD96E5>매혹트론 버섯</color>에게 물체를 공급하는 것은 도움이 되지 않으므로, 물체 낭비를 피하기 위해 <color=#DD96E5>매혹트론 버섯</color>과의 연결을 끊는 것을 잊지 마세요.\n<size=350>\n",
	"419CustomIZ4-10": "<size=18>극성 전환 4-10<size=12></color>\n<alpha=#03>최적 해법: 500 태양 남기기\n<alpha=#00>최적 해법: 700 태양 남기기\n<alpha=#FF><size=320>\n<size=16>마지막 안개 스테이지입니다! 하지만 먼저 지금까지 중 가장 까다로운 상대 중 하나인 <color=#61AB3D>거대 크툴루 버섯</color>을 상대해야 합니다.\n이 녀석은 주기적으로 하수인들을 소환해 좀비를 수중으로 끌고 들어갑니다. 제물용 좀비로 시간을 끌 수는 있지만, 그리 장기적인 전략은 못 되죠.\n소문에 따르면 이 녀석의 <color=#DA8EBA>최면 버섯 형태</color>가 녀석을 크게 약화시킨다고 합니다.\n그러니 <color=#DA8EBA>최면 버섯</color> 카드 패킷을 손에 넣을 수만 있다면, 상황을 반전시킬 수 있을지도 모릅니다.<alpha=#FF>\n<size=360>\n",
	"601CustomIZ特别感谢": "<size=18>\n\n플레이해주셔서 감사합니다!\n\n\n\n\n\n\n\n\n\n\n\n\n\n\n\n\n\n\n<size=18>지금까지 '나, 좀비 어드벤처'였습니다\n<size=12>메인 디렉터 & 기여자: MirteorShower                 도움 주신 분들: 43056721, Shuzhuangshangdehuoyan\n<size=18>특별 감사:\n<size=12>Lanpiaopiaofly 및 모든 Fusion 개발자분들\n<u>Aikemaobohe, Hongshaodaiyu (베타 테스트)</u>    <u>Infinity75, Tingyuyehe, WuxuanmengxiX (Better I,Z 에디터)</u>\n그리고 이곳까지 함께해주신 여러분께 감사드립니다.\n<size=18>\n\n\n\n\n\n\n\n\n\n\n\n\n\n\n\n\n\n\n\n\n",
	"602CustomIZ3-10提示": "<size=18>3-10 힌트\n<size=12>(3-10 스테이지를 위한 힌트입니다. 이미 클리어하셨다면 넘어가셔도 좋습니다!)\n<alpha=#00>최적 해법: 700 태양 남기기\n<alpha=#FF><size=320>\n<size=15>비료와 카드 패킷을 사용해 대형 외부에서 다섯 번째 마법 양파 토끼를 조합한 뒤,\n그를 리더로 설정하면 대형 내부에 있는 것들이 공격하는 것을 방지할 수 있습니다.\n조합 경로: [연꽃잎 + 비료 → 연꽃 고양이]  [연꽃 고양이 + <i>캣 스쿼시</i> → 마법 고양이 둥지]  [마법 고양이 둥지 + <i>식물 상자</i> → 마법 양파 토끼] \n캣 스쿼시: 파멸의 가스 버섯을 활성화해 6번 레인의 캣 스쿼시가 목표를 빗나가게 하세요.\n식물 상자: 비료를 좀비 연불꽃에게 공급하세요.<alpha=#FF>\n<size=360>\n",
	"701CustomIZ1-9B": "<size=18>시간의 잔디밭 1-9B\n<size=12><alpha=#FF>제작자: MirteorShower, 최적 해법: 400 태양 남기기\n<size=6><alpha=#00>awa\n<size=18><alpha=#FF>\n\n\n\n\n\n\n\n\n\n\n\n\n\n\n\n\n\nB-Side 레벨에 진입했습니다. 핵심 메커니즘은 메인 스테이지와 유사하지만—\n<u>1. 난이도가 더 높고 실수의 여지가 적으며, 최적의 남은 태양 수치가 표시됩니다.</u>\n<u>2. 메인 스테이지의 메커니즘을 더욱 확장합니다.</u>\n<size=18>상당한 도전이 될 수 있으니, 자신만의 속도에 맞춰 진행해 보세요.\n\n\n\n\n\n\n\n\n\n\n\n\n\n\n\n\n\n\n\n\n",
	"702CustomIZ1-10B": "<size=18>시간의 잔디밭 1-10B\n<size=12><alpha=#FF>제작자: MirteorShower, 최적 해법: 575 태양 남기기\n<size=6><alpha=#00>awa\n<size=18><alpha=#FF>\n\n\n\n\n\n\n\n\n\n\n\n\n\n\n\n\n\n체리 개틀링이 돌아왔습니다! 설욕전을 위해 업그레이드된 팀을 이끌고 온 모양이군요.\n잔디밭 후방의 미식축구 개틀링을 제외하면 원래 팀과 크게 달라 보이진 않습니다만...\n<u>파괴하려면 6번의 체리 폭발이 필요합니다.</u>\n양옆에 있는 태양 스쿼시의 부활 메커니즘을 이용해 미식축구 개틀링에게 여러 번 대미지를 줄 수 있습니다.\n하지만 태양 스쿼시를 부활시킬 때 드는 비용을 항상 염두에 두세요...\n\n\n\n\n\n\n\n\n\n\n\n\n\n\n\n\n\n\n\n\n",
	"703CustomIZ3-6B": "<size=18>흐름 만들기 3-6B<size=12>\n<alpha=#FF>제작자: 爱嗑猫薄荷, 최적 해법: 525 태양 남기기\n<alpha=#00>최적 해법: 800 태양 남기기\n<alpha=#00>.<alpha=#FF><size=18>\n\n\n\n\n\n\n\n\n\n\n\n\n\n\n\n\n\n<size=15>안돼요! 식물들이 승마 미식축구 개틀링 좀비를 위해 완전한 죽음의 함정을 파놓았습니다.\n하지만 잠깐 - 화염 옥수수 대포도 가져왔다고요? 맵을 잘 살펴보고 조합 기회를 찾으세요.\n팁: 태양 대제 호두가 태양을 더 생성하는 데 도움이 될까요? 아니면 멀리서 좀비를 최면시키면 다른 좀비들이 몰래 지나갈 수 있을까요?\n추신: 조합 가능한 모든 식물은 실제로 중요합니다. 신중하게 생각하세요.<size=18>\n\n\n\n\n\n\n\n\n\n\n\n\n\n\n\n\n\n\n\n\n",
	"704CustomIZ4-7B": "<size=18>극성 전환 4-7B<size=12>\n<alpha=#FF>제작자: 憋坏灯磁, MirteorShower, 최적 해법: 475 태양 남기기\n<alpha=#00>최적 해법: 800 태양 남기기\n<alpha=#00>.<alpha=#FF><size=18>\n<size=310>\n<size=15>양동이 외에도, <color=yellow>광부 좀비의 곡괭이(자석 버섯으로 획득)</color>는 특정 자석 식물들과 조합하여 특별한 효과를 낼 수 있습니다. 예를 들어:\n[자석 스타푸르츠 + 곡괭이 → 곡괭이 스타푸르츠]: 더 이상 좀비를 막지 않음\n[자석 호박 + 곡괭이 → 광부 호박]: 광부 좀비를 지상으로 강제 부상시킴\n광부 좀비가 타일 중간에 있을 때 광부 호박을 조합하면, 호박 안의 식물들에게 공격받지 않습니다.</color>\n<size=360>\n",
	"901CustomIZ原汁原味": "I, Zombie 퍼즐에 오신 것을 환영합니다! 권장 난이도를 따라주세요. 그렇지 않으면 클리어가 불가능해지거나 너무 쉬운 꼼수가 발생할 수 있습니다!\n이 첫 번째 스테이지는 매우 쉬우며, 레벨은 쉬운 것부터 어려운 순으로 배치되어 있습니다.\n좀보니의 빙결 면역과 장대 좀비를 활용하여 레벨을 클리어하세요~\n작성자: Catnip_Lover, 최적 해법: 400 태양 남기기",
	"902CustomIZ牢不可破": "힌트: 스파이크위드의 타이어 터뜨리기 메커니즘을 다시 확인하세요!\n좀보니: 더 빠르지만 스파이크위드를 1개만 처리할 수 있습니다. 봅슬레이 좀비: 더 느리지만 2번까지 버틸 수 있습니다.\n작성자: Flame on the Stump, 최적 해법: 425 태양 남기기",
	"903CustomIZ相生相克": "힌트: 얼음 키다리 호두 좀비는 빙결에 면역입니다. 체리 호두 좀비는 체리 폭발로부터 피해를 적게 입습니다. 난이도 4는 해결 가능하지만, 난이도 0은 불가능합니다.\n스카이콩콩 좀비와 은산잎를 이용해 스쿼시를 따돌릴 수 있습니다. 스쿼시가 공중에 떠 있는 동안 타이밍을 맞추세요.\n작성자: Zero_Value, 최적 해법: 200 태양 남기기 (희한한 먹깨비 상호작용)",
	"904CustomIZ静待时机": "전설에 따르면 두 번째 유성이 25 태양을 아끼고자 하는 당신의 소원을 들어줄 것입니다!\n팁: 게임 속도가 빠를 때 돌고래 라이더 좀비는 뇌를 놓칠 수도 있습니다.\n작성자: Feng Tianyu-, 최적 해법: 450 태양 남기기",
	"905CustomIZ压路机": "얼음공/화염구가 경사면을 따라 굴러가며 라인 전체를 청소합니다!\n메카 호두 좀비가 처치될 때 이것들을 생성하니 타이밍을 잘 맞추세요!\n힌트: 적절한 타이밍에 파멸의 가스 버섯을 작동시켜 얼음공/화염구를 생성하세요!\n작성자: Ai Ke Mao Bo He, 최적 해법: 400 태양 남기기",
	"906CustomIZ群英荟萃": "선인장 호박은 50의 고정 피해를 반사합니다! 학술지 좀비가 그들의 강력한 카운터입니다!\n힌트: 5번째 라인에서 좀비 하나를 저주 버섯과 교환하세요.\n작성자: waiguasqqe, 최적 해법: 250 태양 남기기",
	"907CustomIZ轮番上阵": "각 좀비의 능력을 최대한 활용하여 성가신 멀티 라인 공격자들부터 먼저 처리하세요!!\n경고: 게임 속도가 빠를수록 돌고래 라이더 좀비에게 버그가 발생할 수 있습니다!!!\n작성자: Ai Ke Mao Bo He, 최적 해법: 400 태양 남기기 (난이도 0)",
	"908CustomIZ深入敌后": "3번째 라인의 마법 고양이 둥지와 2번째 라인의 캣테일 걸이 당신을 심각하게 망쳐놓을 수 있습니다! 영리하게 대처하세요!\n이 좀비들은 보통 뇌를 먹을 수 없으니, 가능한 방법을 찾아보세요!\n그리고 4번째 라인의 바보 캣 스쿼시를 잊지 마세요! 은산잎으로 그녀를 따돌리세요!\n작성자: wo shi fvv, 최적 해법: 175 태양 남기기",
	"909CustomIZ提前降落": "은산잎과 자석으로 스카이콩콩 좀비들을 스카이콩콩에서 떨어뜨리세요!\n힌트: 우울 버섯을 폭파하고 황금 마늘을 사용하여 좀비 하나로 뇌 2개를 먹으세요.\n작성자: yong diao gou diao diao gou, 최적 해법: 150 태양 남기기",
	"910CustomIZ火爆艺术": "불꽃 옥수수 대포의 주입 메커니즘을 당신에게 유리하게 활용할 방법을 생각해보세요!\n힌트: 삼발슈터에게 파이로 폭발을 가하면 가르간투아가 임프를 던지게 할 수 있습니다! 지뢰 할라페뇨가 당신을 위해 흑요석 키다리 호두를 \"수축\"시키는 데 도움을 줄 수 있습니다 :3\n해바라기를 폭파하지 마세요! 결국 더 많은 태양을 잃게 될 것입니다.\n작성자: Ai Ke Mao Bo He, 최적 해법: 225 태양 남기기",
	"911CustomIZ篮球与樱机": "힌트: 더블블래스트 패션푸르츠의 궁극기는 좀비들을 수축시킵니다 - 놀라운 효과를 확인하세요!\n장대 좀비의 점프 거리를 단축하여 보통은 닿지 않는 식물을 작동시키고, 심지어 뒤쪽의 히트박스까지 파고들 수 있습니다 :3\n1번째 라인의 연불꽃을 처리하기 위해 4번째 라인에 체리폭탄 펄트 좀비가 필요할 것입니다.\n작성자: Ai Ke Mao Bo He, 최적 해법: 300 태양 남기기",
	"912CustomIZ饮鸩止渴": "최적 해법에 도달하고 싶다면 장기적으로 생각하세요!\n이 레벨에서는 은/황금 식물들을 잘 활용해야 합니다!\n좀보니가 뇌를 먹으러 가는 동안 2번째 라인에 장대 좀비를 보내야 한다고 생각할 수도 있고,\n그렇지 않으면 풍선 좀비가 유일한 선택지라고 생각할 수도 있습니다. 하지만 정말 그럴까요?\n작성자: Xiao Dong Wan De Hao, 최적 해법: 400 태양 남기기",
	"913CustomIZ黄金冻结": "장대 좀비가 우울 버섯을 먹을 수 있는 방법을 찾아보세요! 적절한 타이밍에 겁쟁이 버섯을 깜짝 놀라게 만드세요! awa\n힌트: 좀비 하나를 감자 지뢰와 교환하고 1번째 라인에서 장대 좀비를 보내 우울 버섯을 먹으세요.\n얼음 최면 버섯으로 일반 좀비들을 얼린 다음, 감속되는 동안 장대 좀비가 우울 버섯을 먹게 하세요.\n4번째 라인에서 황금 해바라기를 먹는 좀비를 희생시켜야 합니다. awa\n작성자: Cuo Luan_Ling Zhi, 최적 해법: 50 태양 남기기",
	"914CustomIZ各显神通1": "각 좀비는 한두 번씩만 필요할 것입니다.\n힌트: 자석 버섯이 쓸모를 다하면 치워버리세요 :3\n광부 좀비의 타이밍을 맞출 필요는 없지만, 최적 해법에 도달하려면 그렇게 하세요.\n참고: 실수할 경우를 대비해 번지 좀비 하나 분량의 태양을 추가로 드렸습니다. 총 3마리의 번지 좀비를 사용할 수 있습니다.\n작성자: Ai Ke Mao Bo He, 최적 해법: 400 태양 남기기",
	"915CustomIZ各显神通2": "각 좀비는 정확히 한 번씩만 필요할 것입니다\n힌트: 미식축구 좀비와 일반 좀비는 뇌를 먹기 위한 백업입니다!\n참고: 각 라인에 다른 좀비들을 시도해 보면 해법을 찾을 수 있을 거예요 :3\n작성자: Ai Ke Mao Bo He, 최적 해법: 0 태양 남기기",
	"916CustomIZ步步紧逼": "깜짝 상자 폭발은 100만 데미지를 입힙니다! 이것으로 성가신 식물들을 날려버리세요!\n힌트: 최선의 결과를 위해 혹한 방패병을 뒤쪽에 배치하세요! 식물들을 얼려서 번지 좀비가 평소에는 훔칠 수 없는 식물들을 훔치게 하세요.\n참고: 깜짝 상자 좀비는 처음에만 유용하며, 그 이후에는 필요 없습니다!\n작성자: Ai Ke Mao Bo He, 최적 해법: 150 태양 남기기",
	"917CustomIZ车水马龙": "팁: 먹깨비는 장대 좀비를 먹을 수 없습니다. 황금 마늘은 라인 변경을 강제할 수 있습니다. 더블블래스트 패션푸르츠는 키가 작은 좀비를 조준할 수 없습니다.\n힌트: 만약 5번째 라인의 좀 더 오른쪽에 장대 좀비를 배치하면 어떻게 될까요? 저주 폭발로 2번째 라인의 스파이크락을 제거할 수 있습니다.\n참고: 장대 좀비가 좀보니를 대신해 4번째 라인의 풋체리피터를 뛰어넘을 수도 있습니다.\n작성자: Hong Shao Dai Yu, 최적 해법: 125 태양 남기기",
	"918CustomIZ冰封航线": "빠른 것이 항상 더 나은 것은 아닙니다.\n전략적으로 둔화 효과를 활용하세요.\n작성자: Shu Zhuang Shang De Huo Yan",
	"919CustomIZ小丑回魂": "<size=20>깜짝 상자 폭발의 범위는 1.5칸입니다!\n저주 좀비가 폭발할 때 자신이 있는 칸의 식물을 파괴합니다!\n블로버 호박 주변에서 풍선 좀비의 타이밍을 잘 맞추세요!\n작성자: Xiao Dong Wan De Hao, 최적 해법: 200 태양 남기기",
	"920CustomIZ选择解谜": "<size=18>식물 상자 덕분에 하나의 가격으로 두 개의 나, 좀비 퍼즐을 즐겨보세요!!\n참고: 불꽃 옥수수 대포로 해바라기를 날려버리는 것은 아무런 이득이 없습니다.\n작성자: Xiao Dong Wan De Hao, 최적 해법: 850 (얼음 옥수수 대포), 800 (화염 옥수수 대포) 태양 남기기",
	"921CustomIZ一碰就碎": "설귀는 마늘 화분이나 최면 버섯류들과 같이 체력은 낮지만 물어뜯기에 저항력이 있는 식물들을 상대할 수 있습니다!\n작성자: Wo Shi FVV, 최적 해법: 250 태양 남기기",
	"922CustomIZ出其不意": "단 2열뿐인 방어를 얕보지 마세요! 적어도 7가지 이상의 해결 방법이 있습니다! :3\n힌트: 배구동토의 폭발은 풍선 좀비를 터뜨리고 사다리를 제거할 수 있습니다 :3 폭발 버섯은 4번째 라인의 좀비들에게 겁을 먹을 수도 있습니다.\n참고: 1번째 라인은 마치 시한폭탄처럼 보이는군요.\n작성자: Ai Ke Mao Bo He, 최적 해법: 75 태양 남기기",
	"923CustomIZ跑酷高手": "미식축구 깃발 좀비는 꼬마 얼음 버섯에 부딪히면 회피 구르기를 하지 않습니다!\n겁쟁이 버섯을 효율적으로 활용하여 미식축구 깃발 좀비가\n모든 해바라기와 뇌를 먹을 수 있도록 도와주세요!\n작성자: Yong Diao Gou Diao Diao Gou, 최적 해법: 0 태양 남기기",
	"924CustomIZ巨人之手": "퓨전 버전의 가르강튀아는 공격 범위가 더 길며, 식물을 발동시키지 않고 내리칠 수 있습니다~\n힌트: 황금 옥수수 펄트의 궁극기는 1,800 데미지를 입히며, 가르강튀아(5번째 라인)에게서 임프를 빠르게 떼어낼 수 있습니다.\n임프가 없는 가르강튀아도 여전히 방향을 틀어 추가적인 뇌를 내리칠 수 있습니다.\n참고: 연금술사 우산잎은 가르강튀아를 밀쳐낼 수 있고, 추운 버섯은 풍선 좀비를 얼릴 수 있습니다.\n작성자: Ai Ke Mao Bo He, 최적 해법: 225 태양 남기기",
	"925CustomIZ功能冻结": "예티 좀비의 빙결은 식물의 능력을 정지시킬 수 있습니다! :3\n힌트: 얼어붙은 스파이크락은 타이어를 터뜨릴 수 없고, 얼어붙은 선인장 우산잎은 풍선 좀비를 터뜨릴 수 없으며, 얼어붙은 자석 버섯은 금속 물체를 끌어당길 수 없습니다 :3\n참고: 광부 좀비가 적절한 위치에 있을 때 자석 버섯을 재가동시키기 위해 파멸의 가스 버섯으로 예티 좀비를 희생시키면 어떨까요?\n작성자: Ai Ke Mao Bo He, 최적 해법: 225 태양 남기기",
	"926CustomIZ空袭": "풍선 좀비를 터뜨리고 뇌를 먹게 할 기발한 방법을 찾아보세요!\n힌트: 삼지창 좀비는 한 번만 필요합니다.\n참고: 반드시 난이도 0에서 플레이해 주세요! 난이도 4나 난이도 5에서는 클리어가 불가능할 수 있습니다.\n작성자: Ai Ke Mao Bo He, 최적 해법: 225 태양 남기기",
	"927CustomIZ时空医师": "<size=18>3번째와 4번째 라인에 마늘 화분이 없는 마늘들이 있지만, 이 레벨을 클리어하는 데 운은 필요하지 않습니다!\n크로노포탈 좀비의 무한 소환 능력과 그가 떨어뜨리는 크로노 코어를 잘 활용하여 이 레벨을 해결하세요!\n작성자: Yong Diao Gou Diao Diao Gou, Xiao Dong Wan De Hao, 최적 해법: 100 태양 남기기",
	"928CustomIZ谁是内鬼": "가장 많은 수의 사기꾼들이 등장하는 레벨입니다!\n힌트: 체리 드론 호박을 폭발시킬 수 있는 식물이 있습니다.\n참고: 1번째 라인에서 광부 좀비를 사용하면 어떤 일이 벌어질까요?\n작성자: Ai Ke Mao Bo He, 최적 해법: 325 태양 남기기",
	"929CustomIZ矿镐难题": "이 레벨을 클리어하기 위해 스티브 좀비와 예티를 조율해 보세요!\n힌트: 스티브 좀비의 특별한 특성을 활용해 경로를 개척하세요!\n참고: 서로 다른 종류의 스티브 좀비가 있어도 레벨 해결에는 영향을 주지 않습니다.\n작성자: Ai Ke Mao Bo He, 최적 해법: 325 태양 남기기",
	"930CustomIZ窝被套珞了": "바보 냥코! 우산잎을 사용해서 캣 스쿼시를 따돌려 보세요!\n힌트: 캣 스쿼시는 뒤를 보지 못합니다. 자석 버섯을 흉내 내세요 :3. 황금 화분으로 연결된 우산잎들을 조심하세요!\n참고: 바보 같은 캣 스쿼시! 2번째 라인에는 광부 좀비가 필요 없답니다 야옹 (황금 마늘이 있으니까요)~\n작성자: Ai Ke Mao Bo He, 최적 해법: 125 태양 남기기",
	"931CustomIZ中门对狙": "양동이슈터와 저격콩의 결투! 잠깐, 일반 좀비는 왜 여기에 있는 거죠!?\n우산잎, 감자 지뢰, 옥수수 대포 그리고 파멸 먹깨비의 특성을 활용해 이 레벨을 통과하세요!\n체리 감자 지뢰가 생성한 감자 지뢰가 활성화되기 전에 처치하세요!\n작성자: Cuo Luan_Ling Zhi, 최적 해법: 125 태양 남기기",
	"932CustomIZ航空引导": "<size=15>안돼요! 호박 착륙장입니다! 이 호박은 비행선들의 위치를 엉망으로 만들 테니, 상황이 걷잡을 수 없어지기 전에 터뜨리세요!\n이 레벨을 위해 알아두어야 할 사항들입니다:\n1. 황금 마늘을 사용해 좀비 1마리로 뇌 2개를 먹으세요. 2. 촉소된 장대 좀비는 식물을 뛰어넘을 수 없습니다.\n3. 스타푸르츠 호두는 연불꽃을 비료로 바꾸는 것을 도와줄 수 있습니다. 4. 파멸 폭발은 같은 타일에 있는 다른 모든 식물들을 파괴합니다.\n힌트: 5번째 라인의 연불꽃은 장대 좀비를 막는 용도일 뿐 다른 용도는 없습니다.\n작성자: Xiao Dong Wan De Hao, 최적 해법: 175 태양 남기기",
	"933CustomIZ阳光大盗": "<size=20>안돼요, 솔라푸르츠입니다! 이들이 우리의 태양을 모두 훔쳐갈 거예요! 빨리 처치하세요!\n작성자: Xiao Dong Wan De Hao, 최적 해법: 500 태양 남기기",
	"934CustomIZ阳光大盗2": "<size=18>스쿼시 좀비로 마늘을 처리하세요! 5번째 라인의 체리 개틀링 드론을 파멸시키세요.\n불꽃 황제 호두의 체력을 줄이기 위해 볼링 호두를 소환하세요!\n그들은 회복하기 위해 15 태양을 훔치므로, 그들을 상대하기 전에 모든 태양을 사용하세요!\n작성자: Wo Shi fvv, Xiao Dong Wan De Hao, 최적 해법: 325 태양 남기기",
	"935CustomIZ另辟蹊径": "경고: 이 레벨은 매우 어렵습니다! 여러 번 시도해도 클리어할 수 없다면 무리하지 말고 건너뛰셔도 좋습니다.\n\n\n\n\n\n\n\n\n\n\n\n\n\n\n\n\n\n\n이 레벨은 게임에 대한 다양한 지식을 테스트합니다! 힌트: \n1번째 라인: 광부 좀비가 자석 호박을 통과하게 한 뒤, 광부 호박을 조합하여 선인장 호박을 우회하세요.\n4번째 라인: 사다리 좀비를 다치게 하지 않으면서 사다리를 제거할 수 있도록 대포 발사 타이밍을 맞추세요.\n다양한 좀비들을 기발하게 활용하여 레벨에서 승리하세요!\n작성자: Hong Shao Dai Yu, 최적 해법: 50 태양 남기기\n\n\n\n\n\n\n\n\n\n\n\n\n\n\n\n\n\n\n\n",
	"936CustomIZ扶梯风波": "비료와 히카매지션의 능력을 잘 활용하여 식물을 조합하세요!\n옥수수 대포를 사용하여 사다리를 제거하세요! 용기 호박 안에 있는 쌍둥이 해바라기에 도달할 방법을 찾아보세요!\n작성자: Xiao Dong Wan De Hao, 최적 해법: 300 태양 남기기",
	"937CustomIZ跳跳舞会": "멜론콩콩 좀비가 대부분의 방어선을 뛰어넘게 하세요!\n힌트: 우산잎을 기발하게 활용하세요.\n참고: 이제 다른 조작법들은 이미 익숙해지셨을 겁니다.\n작성자: Ai Ke Mao Bo He, 최적 해법: 225 태양 남기기",
	"938CustomIZ禁止套娃": "<size=15>박스 좀비들의 체력은 정말 어마어마합니다! 이들을 이용해 호두들을 밀어붙이고 즉사기를 견뎌보세요!\n3번째 라인의 최면 먹깨비는 최면 버섯들을 만들 수 있습니다;\n체리폭탄 펄트를 3번째 라인에 배치하면 2번째 라인의 촉촉꽃니와 4번째 라인의 자석 선인장을 처리할 수 있고,\n4번째 라인에 있는 불꽃 키다리 호두의 체력을 줄여서 상자 머리가 스파이크 호두를 뚫고 지나갈 수 있게 합니다!\n작성자: Xiao Dong Wan De Hao, 최적 해법: 125 태양 남기기",
	"939CustomIZ蘑菇迷阵": "<size=16>최면 먹깨비를 사용하여 최면 버섯 씨앗 패킷을 얻을 방법을 찾아보세요!\n힌트: 최면 자석은 능동적으로 금속을 끌어당기는 능력을 상실합니다!\n꼬마 최면 버섯은 혹한 방패병으로 대처할 수 있습니다!\n2번째 라인에 광부 좀비를 보내 꼬마 호두 버섯들을 제거하세요!\n작성자: Decepticons_, 최적 해법: 50 태양 남기기",
	"940CustomIZ艺术就是爆炸": "힌트: 화염 폭발은 풍선들도 터뜨릴 수 있습니다 :3\n참고: 해바라기를 폭파시키는 것은 의미가 없습니다.\n작성자: Ai Ke Mao Bo He, 최적 해법: 125 태양 남기기",
	"941CustomIZ手动换挡": "팁: 녹슨 사다리는 최대 8,000의 피해를 전이시킬 수 있으며 호박 안의 식물들도 죽일 수 있습니다!\n좀비들이 너무 많은 피해를 입지 않도록 연발 리피터의 공격 모드를 변경하는 것을 잊지 마세요!\n1번째 라인의 블로버 호박에 식물을 배치하고 마늘이 마늘 블로버가 될 때까지 기다리세요.\n그러면 치킨 좀키가 4번째 라인과 5번째 라인 모두의 뇌를 먹을 수 있게 됩니다!\n작성자: Decepticons_, 최적 해법: 200 태양 남기기",
	"942CustomIZ盖世神偷": "번지 좀비를 기발하게 활용하여 승리하세요! 4번째 라인의 장애물을 제거하기 위해\n꼬마 얼음 버섯에 의해 번지 좀비가 얼어붙은 후 마늘 우산잎을 조합하세요!\n높은 빛 레벨에서의 발광 스타푸르츠의 능력은 우리 좀비 배치에도 영향을 미칩니다!\n작성자: Decepticons_, 최적 해법: 75 태양 남기기",
	"943CustomIZ逆向思维": "저격콩을 조심하세요! 따라쟁이의 도움을 받으면 이 위협을 빠르게 무력화할 수 있습니다.\n힌트: 체리폭탄 펄트 좀비는 결국 우산잎을 뚫을 수 있으며, 탄약이 떨어지면 식물을 짓밟을 수도 있습니다!\n작성자: Yu Shan Ya, 최적 해법: 200 태양 남기기",
	"944CustomIZ弃子争先": "모든 퓨전은 우리의 것이다!!\n함부로 깔지 말고 신중하게 생각하세요! 전투가 길어지는 것을 피해야 합니다!\n심는 속도가 느려지는 것에 주의하세요 (해법을 보장할 수 없습니다)!\n작성자: Shu Zhuang Shang De Huo Yan, 최적 해법: 675 태양 남기기",
	"945CustomIZ套娃走梯": "<size=20>박스 좀비는 사다리를 제거하는 폭발을 견뎌낼 수 있습니다!\n이 메커니즘을 잘 활용하여 이 레벨을 클리어하세요!\n작성자: Wo Shi FVV, Xiao Dong Wan De Hao, 최적 해법: 25 2 태양 남기기",
	"946CustomIZ镜像系统": "빛나는 화분의 황금 식물들이 서로 동기화되지 않도록 주의하세요! 황금 커피콩은\n이 식물들의 궁극기를 한꺼번에 발동시킬 것입니다. 필요하다면 화력을 분산시키기 위해 추가 좀비를 배치하세요!\n작성자: MirteorShower, 최적 해법: 325 태양 남기기",
	"947CustomIZ王牌翻滚": "보세요! 비행선입니다! 이제 레벨이 우리에게 유리해졌습니다.\n힌트: 특정 금속 물체를 사용하여 잠자석 버섯을 깨우세요!\n작성자: Shu Zhuang Shang De Huo Yan, 일관된 해법: 275 태양 남기기, 행운의 해법: 550 태양 남기기",
	"948CustomIZ冰樱传递": "전략적으로 얼음 옥수수 대포를 발사하여 얼린 체리를 만들고, 좀비들을 위해 체리를 막아내세요!\n길을 가로막는 식물들을 제거하는 것을 잊지 마세요!\n나중에 황금 우산잎으로 멜론콩콩 좀비를 튕겨내기 위해, 미리 마이더스 우산잎으로 코인을 만들어야 합니다!\n1 황금 동상 = 3000 코인\n작성자: Decepticons_, 최적 해법: 100 태양 남기기",
	"949CustomIZ鸟尽弓藏": "경고: 고난이도 레벨입니다. 주의해서 진행하세요.\n\n\n\n\n\n\n\n\n\n\n\n\n\n\n\n\n\n\n\n자석 블로버는 곡괭이를 끌어당길 수 있습니다. 광부 좀비의 타이밍을 잘 맞추는 것을 잊지 마세요!\n힌트: 까다로운 부분은 5번째 라인의 쌍둥이 해바라기입니다. 양동이콥터로 잠입하여 적절한 위치에서 격추되도록 하세요.\n블로버 호박에 비료를 주어 즉시 다음 블로버를 생성하게 하세요. 호박 착륙장을 합쳐서 양동이콥터를 격추시키세요!\n작성자: Qian Zai Bu Guo Yi Meng, 최적 해법: 100 태양 남기기\n\n\n\n\n\n\n\n\n\n\n\n\n\n\n\n\n\n\n\n\n",
	"950CustomIZ破碎星光": "혹한 방패병은 최면 버섯과 데미지 반사 식물들을 쉽게 상대합니다.\n힌트: \"마늘\"을 사용해 먹깨비질라를 지나갈 방법을 찾아보세요!\n눈덩이를 반사하기 위해 혹한 방패병을 사용할 필요는 없습니다.\n작성자: MirteorShower, 최적 해법: 250 태양 남기기",
	"951CustomIZ有猫先打猫尾草": "캣테일의 유도 능력을 이용해 풍선을 터뜨리고 신문지를 부수세요!\n캣테일이 더 이상 필요 없어지면 고래 라이더 예티를 보내 처리하세요!\n작성자: Xiao Dong Wan De Hao, 최적 해법: 250 태양 남기기\n참고: 캣테일과 캣 스쿼시를 합쳐서 마법 고양이 둥지를 만들지 마세요! 즉시 실패합니다, ㅋㅋㅋ.",
	"952CustomIZ水调歌头": "조합을 사용하여 장애물을 제거하고 좀비가 돌파할 기회를 만드세요!\n미식축구 개틀링은 미식축구 깃발 좀비를 도망치게 만듭니다! 자석 호두를 사용하여 투사체를 모으세요!\n시작이 다소 느릴 수 있습니다(뽀꾸 버섯이 나올 때까지 기다려야 합니다). 나중에 개선될 예정입니다!\n작성자: Decepticons_, 최적 해법: 125 태양 남기기 (일관)",
	"953CustomIZ咒梯风波": "<size=18>녹슨 사다리 + 저격콩의 헤드샷 콤보로 흑요석 키다리 호두와 기가 메카 호두를 즉시 처치하세요!\n메카 가르강튀아를 보내 저격콩의 공격을 모으고, 호박 속 약한 식물들이 피해를 가로채지 못하게 하세요!\n극복 스테이지을 이전에 플레이해봤다면 캣 스쿼시 + 최면 버섯 전략에 익숙할 것입니다.\n작성자: Xiaodong had a good time, 최적 해법: 150 태양 남기기",
	"954CustomIZ定点碰撞": "<size=18>풀 체력인 아기 설귀는 체력 300인 식물과 1대1로 교환할 수 있습니다! 은 마늘로 교환 방향을 바꿀 수 있습니다!\n꼬마 설귀가 라인을 바꿀 때, 호박 속의 식물까지 칠 수도 있어요!\n호박에 붙어 있는 사다리는 안에 있는 식물이 파괴되거나 조합시 제거됩니다!\n참고: 당신에게는 쌍둥이 해바라기 하나와 5000 코인(은 동상 5개)에 해당하는 오차 범위가 있습니다.\n작성자: Xiaodong had a good time, 최적 해법: 425 태양 남기기",
	"955CustomIZ转移阵地": "경고: 매우 어려운 레벨입니다. 주의해서 진행하거나 난이도 5를 시도해 보세요.\n\n\n\n\n\n\n\n\n\n\n\n\n\n\n\n\n\n\n\n\n체리 폭탄, 감자 지뢰, 할라피뇨, 황금 우산잎 사용법에 대해 잘 알고 있어야 합니다.\n작성자: 43056721, 최적 해법: 300 태양 남기기\n\n\n\n\n\n\n\n\n\n\n\n\n\n\n\n\n\n\n\n\n\n",
	"956CustomIZ天梯计划": "경고: 난이도가 매우 높으니 주의하여 진행하십시오. (난이도 5 고정)\n\n\n\n\n\n\n\n\n\n\n\n\n\n\n\n\n\n\n\n이 레벨에는 특별한 장치가 많지 않지만, 높은 정확도와 전략적 요구 사항이 있습니다.\n이 단계와 앞으로의 단계를 시도하기 전에 이전 단계를 모두 깨는 것이 좋습니다.\n힌트: 장대 좀비와 사다리 좀비를 조정하고 여러 라인을 동시에 달리세요.\n작성자: 43056721, 최적 해법: 350 태양 남기기 (일관)\n\n\n\n\n\n\n\n\n\n\n\n\n\n\n\n\n\n\n\n\n",
	"957CustomIZ多线并行": "경고: 매우 어려운 레벨입니다. 주의해서 진행하세요!\n\n\n\n\n\n\n\n\n\n\n\n\n\n\n\n\n\n\n\n예전의 광란 버섯과 우울 버섯을 기억하시나요? 같은 방식으로 처리하세요!\n체리 자석 버섯에 여분의 금속 물체를 공급하여 다른 물체를 끌어당기기에는 너무 많은 금속 물체를 \"\"하게 만들 수 있습니다.\n작성자: MirteorShower, 최적 해법: 100 태양 남기기\n\n\n\n\n\n\n\n\n\n\n\n\n\n\n\n\n\n\n\n\n",
	"958CustomIZ爆破鬼才": "우선 체리폭탄 펄트 좀비와 깜짝 상자 좀비의 스플래시 대미지를 적절히 활용하세요.\n발광 먹깨비는 소화를 마친 후 좀비 1마리를 자신의 라인으로 유인할 수 있습니다. 폭발로부터 발광 먹깨비를 반드시 보호하세요.\n작성자: Decepticons_, 최적 해법: 75 태양 남기기",
	"959CustomIZ机械军团": "마지막 챌린지!\n경고: 매우 어려운 레벨이므로 주의해서 진행하세요.\n\n\n\n\n\n\n\n\n\n\n\n\n\n\n\n\n\n\n메카 호두 좀비의 사망 시 효과를 활용해 레벨을 승리하세요! (얼음공/화염구는 식물을 부수는 데 꼭 필요하지 않습니다.)\n힌트: 요령은 메카 호두의 사망 시 효과를 활성화하는 방법입니다. 1번째 라인의 캣 스쿼시가 유용할 수도 있겠네요!\n권장 난이도로 플레이해 주세요. 난이도 4와 난이도 5는 풀 수 없습니다.\n작성자: Decepticons_, 최적 해법: 100 태양 남기기\n\n\n\n\n\n\n\n\n\n\n\n\n\n\n\n\n\n\n\n\n"
}